funcnodes_opencv/__init__.py
funcnodes_opencv/colornodes.py
funcnodes_opencv/drawing.py
funcnodes_opencv/imageformat.py
funcnodes_opencv/misc_nodes.py
funcnodes_opencv/segmentation.py
funcnodes_opencv/utils.py
funcnodes_opencv/image_operations/__init__.py
funcnodes_opencv/image_operations/arithmetic_operations.py
funcnodes_opencv/image_operations/bitwise_operations.py
funcnodes_opencv/image_operations/matrix_operations.py
funcnodes_opencv/image_operations/normalization_equalization.py
funcnodes_opencv/image_processing/__init__.py
funcnodes_opencv/image_processing/detection_feature_extraction.py
funcnodes_opencv/image_processing/edge_gradient.py
funcnodes_opencv/image_processing/filtering_smoothing.py
funcnodes_opencv/image_processing/geometric_transformations.py
funcnodes_opencv/image_processing/morphological_operations.py
funcnodes_opencv/image_processing/thresholding.py
funcnodes_opencv-0.3.1.dist-info/licenses/LICENSE
funcnodes_opencv-0.3.1.dist-info/METADATA
funcnodes_opencv-0.3.1.dist-info/WHEEL
funcnodes_opencv-0.3.1.dist-info/entry_points.txt
funcnodes_opencv-0.3.1.dist-info/top_level.txt
funcnodes_opencv-0.3.1.dist-info/RECORD
